pybuildit2/__init__.py
pybuildit2/calib.py
pybuildit2/const.py
pybuildit2/lib.py
pybuildit2/log.py
pybuildit2/path.py
pybuildit2/unsafe.py
pybuildit2/cli/__init__.py
pybuildit2/cli/builditctl.py
pybuildit2/gui/__init__.py
pybuildit2/gui/builditctl.py
pybuildit2/gui/config_tab.py
pybuildit2/gui/control_tab.py
pybuildit2/gui/graph_tab.py
pybuildit2/gui/init_tab.py
pybuildit2/gui/log_tab.py
pybuildit2/gui/main_panel.py
pybuildit2/gui/side_panel.py
pybuildit2/gui/top_panel.py
pybuildit2/gui/util.py
pybuildit2/gui/config/default_params.yml
pybuildit2/gui/config/params_sample.yml
pybuildit2/gui/config/servo.yml
pybuildit2/gui/config/system.yml
pybuildit2/gui/config/unsafe-servo.yml
pybuildit2/gui/imgs/LED-GREEN.gif
pybuildit2/gui/imgs/LED-OFF.gif
pybuildit2/gui/imgs/LED-RED.gif
pybuildit2-1.0.0.dist-info/LICENSE
pybuildit2-1.0.0.dist-info/METADATA
pybuildit2-1.0.0.dist-info/WHEEL
pybuildit2-1.0.0.dist-info/entry_points.txt
pybuildit2-1.0.0.dist-info/top_level.txt
pybuildit2-1.0.0.dist-info/RECORD
