Metadata-Version: 2.1
Name: pybuildit2
Version: 1.0.0
Summary: python API for Buildit Actuator (For Buildit Actuator v1.0.1 and above
Home-page: https://www.smartrobotics.jp/products/buildit
Author: SR
Author-email: info@smartrobotics.jp
License: UNKNOWN
Platform: UNKNOWN
Classifier: Programming Language :: Python :: 3
Classifier: License :: OSI Approved :: MIT License
Classifier: Operating System :: OS Independent
License-File: LICENSE
Requires-Dist: crc8
Requires-Dist: numpy
Requires-Dist: pyserial
Requires-Dist: matplotlib
Requires-Dist: pyyaml
